{
"Name":"Import JLA",
"PrimaryTable":"jlagoldratemaster",
"Columns":[
	{
            "table":"jlagoldratemaster",
            "dbcol":"accountNature",
	     "dbdatatype":"string",
            "csvindex":"1",
            "header":"Acct Nature"
        },
        {
            "table":"jlagoldratemaster",
            "dbcol":"accountType",
	    "dbdatatype":"string",
            "csvindex":"2",
            "header":"AC_TYPE"
        },
	{
            "table":"jlagoldratemaster",
            "dbcol":"ratePeriod",
	    "dbdatatype":"string",
            "csvindex":"3",
            "header":"PERIOD"
        },

        {
            "table":"jlagoldratemaster",
            "dbcol":"rateMonth",
	    "dbdatatype":"string",
            "csvindex":"4",
            "header":"RATE_MONTH"
        },
	{
            "table":"jlagoldratemaster",
            "dbcol":"disbursementFrom",
	    "dbdatatype":"string",
            "csvindex":"5",
            "header":"DISB_FROM"
        },
	{
            "table":"jlagoldratemaster",
            "dbcol":"disbursementTo",
	    "dbdatatype":"string",
            "csvindex":"6",
            "header":"DISB_TO"
        },
	{
            "table":"jlagoldratemaster",
            "dbcol":"carat18",
	    "dbdatatype":"string",
            "csvindex":"7",
            "header":"CARAT_18"
        },
	{
            "table":"jlagoldratemaster",
            "dbcol":"carat19",
	    "dbdatatype":"string",
            "csvindex":"8",
            "header":"CARAT_19"
        },
	{
            "table":"jlagoldratemaster",
            "dbcol":"carat20",
	    "dbdatatype":"string",
            "csvindex":"9",
            "header":"CARAT_20"
        },
	{
            "table":"jlagoldratemaster",
            "dbcol":"carat21",
	    "dbdatatype":"string",
            "csvindex":"10",
            "header":"CARAT_21"
        },
	{
            "table":"jlagoldratemaster",
            "dbcol":"carat22",
	    "dbdatatype":"string",
            "csvindex":"11",
            "header":"CARAT_22"
        },
	{
            "table":"jlagoldratemaster",
            "dbcol":"carat23",
	    "dbdatatype":"string",
            "csvindex":"12",
            "header":"CARAT_23"
        },
	{
            "table":"jlagoldratemaster",
            "dbcol":"carat24",
	    "dbdatatype":"string",
            "csvindex":"13",
            "header":"CARAT_24"
        }
	]
}